setup.cfg
setup.py
deprecationlib/__init__.py
deprecationlib.egg-info/PKG-INFO
deprecationlib.egg-info/SOURCES.txt
deprecationlib.egg-info/dependency_links.txt
deprecationlib.egg-info/top_level.txt