Metadata-Version: 1.1
Name: deprecationlib
Version: 0.1.0
Summary: Python library for assisting with the deprecation process.
Home-page: https://github.com/AndyDeany/deprecationlib
Author: Andrew Dean
Author-email: oneandydean@hotmail.com
License: MIT
Download-URL: https://github.com/AndyDeany/deprecationlib/archive/0.1.0.tar.gz
Keywords: deprecation,deprecated
Platform: UNKNOWN
Classifier: Development Status :: 2 - Pre-Alpha
Classifier: Intended Audience :: Developers
Classifier: Natural Language :: English
Classifier: Programming Language :: Python
Classifier: Programming Language :: Python :: 3
Classifier: Programming Language :: Python :: 3.5
Classifier: Programming Language :: Python :: 3.6
